odoo/addons/project_task_description_template/README.rst
odoo/addons/project_task_description_template/__init__.py
odoo/addons/project_task_description_template/__manifest__.py
odoo/addons/project_task_description_template/data/demo.xml
odoo/addons/project_task_description_template/i18n/it.po
odoo/addons/project_task_description_template/i18n/project_task_description_template.pot
odoo/addons/project_task_description_template/models/__init__.py
odoo/addons/project_task_description_template/models/project_project.py
odoo/addons/project_task_description_template/models/project_task.py
odoo/addons/project_task_description_template/models/project_task_template.py
odoo/addons/project_task_description_template/readme/CONTRIBUTORS.md
odoo/addons/project_task_description_template/readme/DESCRIPTION.md
odoo/addons/project_task_description_template/readme/USAGE.md
odoo/addons/project_task_description_template/security/ir.model.access.csv
odoo/addons/project_task_description_template/static/description/icon.png
odoo/addons/project_task_description_template/static/description/index.html
odoo/addons/project_task_description_template/static/src/js/onchange_confirm_widget.js
odoo/addons/project_task_description_template/tests/__init__.py
odoo/addons/project_task_description_template/tests/test_task_template.py
odoo/addons/project_task_description_template/views/assets.xml
odoo/addons/project_task_description_template/views/project_task_template_views.xml
odoo/addons/project_task_description_template/views/project_views.xml
odoo14_addon_project_task_description_template-14.0.1.0.1.dev5.dist-info/METADATA
odoo14_addon_project_task_description_template-14.0.1.0.1.dev5.dist-info/WHEEL
odoo14_addon_project_task_description_template-14.0.1.0.1.dev5.dist-info/top_level.txt
odoo14_addon_project_task_description_template-14.0.1.0.1.dev5.dist-info/RECORD
